MANIFEST.in
NetPharm.py
README.rst
setup.cfg
setup.py
NetPharm.egg-info/PKG-INFO
NetPharm.egg-info/SOURCES.txt
NetPharm.egg-info/dependency_links.txt
NetPharm.egg-info/requires.txt
NetPharm.egg-info/top_level.txt