Metadata-Version: 1.1
Name: NetPharm
Version: 0.6.1
Summary: A test module for XiChen
Home-page: https://github.com/XiChen-ZOC
Author: XiChen
Author-email: chenx595@mail2.sysu.edu.cn
License: Apache License, Version 2.0
Platform: linux/Windows
Classifier: Development Status :: 3 - Alpha
Classifier: Topic :: Text Processing
Classifier: License :: OSI Approved :: MIT License
Classifier: Programming Language :: Python :: 2
Classifier: Programming Language :: Python :: 2.7
Classifier: Programming Language :: Python :: 3
Classifier: Programming Language :: Python :: 3.5
